bayes_spec/__init__.py
bayes_spec/_version.py
bayes_spec/base_model.py
bayes_spec/cluster_posterior.py
bayes_spec/nuts.py
bayes_spec/optimize.py
bayes_spec/plots.py
bayes_spec/spec_data.py
bayes_spec/utils.py
bayes_spec/models/__init__.py
bayes_spec/models/gauss_model.py
bayes_spec/models/gauss_noise_model.py
bayes_spec-1.9.0.dist-info/licenses/LICENSE
bayes_spec-1.9.0.dist-info/METADATA
bayes_spec-1.9.0.dist-info/WHEEL
bayes_spec-1.9.0.dist-info/top_level.txt
bayes_spec-1.9.0.dist-info/RECORD
