Metadata-Version: 2.4
Name: bayes_spec
Version: 1.9.0
Summary: A Bayesian Spectral Line Modeling Framework for Astrophysics
Home-page: https://github.com/tvwenger/bayes_spec
Author: Trey V. Wenger
Author-email: Trey Wenger <tvwenger@gmail.com>
License: The MIT License (MIT)
Project-URL: Homepage, https://github.com/tvwenger/bayes_spec
Classifier: Programming Language :: Python :: 3
Classifier: License :: OSI Approved :: MIT License
Classifier: Operating System :: OS Independent
Requires-Python: >=3.11
License-File: LICENSE
Requires-Dist: jupyter
Requires-Dist: ipykernel
Requires-Dist: ipywidgets
Requires-Dist: numpy
Requires-Dist: pymc>=5
Requires-Dist: pytensor
Requires-Dist: nutpie
Requires-Dist: numba
Requires-Dist: arviz
Requires-Dist: matplotlib
Requires-Dist: scipy
Requires-Dist: scikit-learn
Requires-Dist: graphviz
Requires-Dist: jaxlib
Requires-Dist: jax
Requires-Dist: blackjax
Requires-Dist: numpyro
Dynamic: author
Dynamic: home-page
Dynamic: license-file
Dynamic: requires-python
